simple_image_tool/__init__.py
simple_image_tool/template/index.html
simple_image_tool-0.0.2.dist-info/entry_points.txt
simple_image_tool-0.0.2.dist-info/WHEEL
simple_image_tool-0.0.2.dist-info/METADATA
simple_image_tool-0.0.2.dist-info/RECORD
